Metadata-Version: 2.1
Name: wadusayshello
Version: 0.1.0
Summary: A test package made for an assignment that prints hello with your name
Home-page: UNKNOWN
License: UNKNOWN
Platform: UNKNOWN
Classifier: Programming Language :: Python :: 3
Requires-Python: >=3.6
